{
	"backtraceGraph" : 
	{
		"commands" : 
		[
			"install",
			"install_project"
		],
		"files" : 
		[
			"OrderBookTests/lib/googletest/googletest/cmake/internal_utils.cmake",
			"OrderBookTests/lib/googletest/googlemock/CMakeLists.txt"
		],
		"nodes" : 
		[
			{
				"file" : 1
			},
			{
				"command" : 1,
				"file" : 1,
				"line" : 120,
				"parent" : 0
			},
			{
				"command" : 0,
				"file" : 0,
				"line" : 322,
				"parent" : 1
			},
			{
				"command" : 0,
				"file" : 0,
				"line" : 325,
				"parent" : 1
			},
			{
				"command" : 0,
				"file" : 0,
				"line" : 347,
				"parent" : 1
			},
			{
				"command" : 0,
				"file" : 0,
				"line" : 347,
				"parent" : 1
			}
		]
	},
	"installers" : 
	[
		{
			"backtrace" : 2,
			"component" : "Unspecified",
			"destination" : "include",
			"paths" : 
			[
				{
					"from" : "OrderBookTests/lib/googletest/googlemock/include",
					"to" : "."
				}
			],
			"type" : "directory"
		},
		{
			"backtrace" : 3,
			"component" : "Unspecified",
			"destination" : "lib",
			"paths" : 
			[
				"lib/libgmock.a"
			],
			"targetId" : "gmock::@05d3934e572ddec06121",
			"targetIndex" : 3,
			"type" : "target"
		},
		{
			"backtrace" : 3,
			"component" : "Unspecified",
			"destination" : "lib",
			"paths" : 
			[
				"lib/libgmock_main.a"
			],
			"targetId" : "gmock_main::@05d3934e572ddec06121",
			"targetIndex" : 4,
			"type" : "target"
		},
		{
			"backtrace" : 4,
			"component" : "Unspecified",
			"destination" : "lib/pkgconfig",
			"paths" : 
			[
				"build/OrderBookTests/lib/googletest/googletest/generated/gmock.pc"
			],
			"type" : "file"
		},
		{
			"backtrace" : 5,
			"component" : "Unspecified",
			"destination" : "lib/pkgconfig",
			"paths" : 
			[
				"build/OrderBookTests/lib/googletest/googletest/generated/gmock_main.pc"
			],
			"type" : "file"
		}
	],
	"paths" : 
	{
		"build" : "OrderBookTests/lib/googletest/googlemock",
		"source" : "OrderBookTests/lib/googletest/googlemock"
	}
}
